phoenix_waitress/__init__.py
phoenix_waitress/__main__.py
phoenix_waitress/adjustments.py
phoenix_waitress/buffers.py
phoenix_waitress/channel.py
phoenix_waitress/compat.py
phoenix_waitress/parser.py
phoenix_waitress/proxy_headers.py
phoenix_waitress/receiver.py
phoenix_waitress/rfc7230.py
phoenix_waitress/runner.py
phoenix_waitress/server.py
phoenix_waitress/task.py
phoenix_waitress/trigger.py
phoenix_waitress/utilities.py
phoenix_waitress/wasyncore.py
phoenix_waitress-2.1.1.4.dist-info/LICENSE.txt
phoenix_waitress-2.1.1.4.dist-info/METADATA
phoenix_waitress-2.1.1.4.dist-info/WHEEL
phoenix_waitress-2.1.1.4.dist-info/entry_points.txt
phoenix_waitress-2.1.1.4.dist-info/top_level.txt
phoenix_waitress-2.1.1.4.dist-info/RECORD
