Metadata-Version: 2.1
Name: phoenix-waitress
Version: 2.1.1.4
Summary: Phoenix fork of the Waitress WSGI server
Home-page: https://github.com/Froggo8311/phoenix_waitress
Author: Zope Foundation and Contributors
Author-email: zope-dev@zope.org
Maintainer: Pylons Project & Froggo8311
Maintainer-email: pylons-discuss@googlegroups.com
License: ZPL 2.1
Project-URL: Documentation, https://docs.pylonsproject.org/projects/waitress/en/latest/index.html
Project-URL: Changelog, https://docs.pylonsproject.org/projects/waitress/en/latest/index.html#change-history
Project-URL: Issue Tracker, https://github.com/Froggo8311/phoenix_waitress/issues
Keywords: waitress wsgi server http phoenix
Platform: UNKNOWN
Classifier: Development Status :: 6 - Mature
Classifier: Environment :: Web Environment
Classifier: Intended Audience :: Developers
Classifier: License :: OSI Approved :: Zope Public License
Classifier: Programming Language :: Python
Classifier: Programming Language :: Python :: 3
Classifier: Programming Language :: Python :: 3.7
Classifier: Programming Language :: Python :: 3.8
Classifier: Programming Language :: Python :: 3.9
Classifier: Programming Language :: Python :: 3.10
Classifier: Programming Language :: Python :: Implementation :: CPython
Classifier: Programming Language :: Python :: Implementation :: PyPy
Classifier: Operating System :: OS Independent
Classifier: Topic :: Internet :: WWW/HTTP
Classifier: Topic :: Internet :: WWW/HTTP :: WSGI
Requires-Python: >=3.7.0
Provides-Extra: docs
Requires-Dist: Sphinx (>=1.8.1) ; extra == 'docs'
Requires-Dist: docutils ; extra == 'docs'
Requires-Dist: pylons-sphinx-themes (>=1.0.9) ; extra == 'docs'
Provides-Extra: testing
Requires-Dist: pytest ; extra == 'testing'
Requires-Dist: pytest-cover ; extra == 'testing'
Requires-Dist: coverage (>=5.0) ; extra == 'testing'
